Metadata-Version: 2.1
Name: odoo14-addon-hr-employee-lastnames
Version: 14.0.3.0.0
Summary: Split Name in First Name, Father's Last Name and Mother's Last Name
Home-page: https://github.com/OCA/hr
Author: Vauxoo, Odoo Community Association (OCA)
Author-email: support@odoo-community.org
License: AGPL-3
Platform: UNKNOWN
Classifier: Programming Language :: Python
Classifier: Framework :: Odoo
Classifier: License :: OSI Approved :: GNU Affero General Public License v3
Requires-Python: >=3.6
Requires-Dist: odoo14-addon-hr-employee-firstname
Requires-Dist: odoo (<14.1dev,>=14.0a)
